pydantic_dop/__init__.py
pydantic_dop-0.0.1.dist-info/METADATA
pydantic_dop-0.0.1.dist-info/WHEEL
pydantic_dop-0.0.1.dist-info/RECORD
