Metadata-Version: 2.1
Name: pydantic-dop
Version: 0.0.1
Summary: Data Oriented Programming with Pydantic Models.
Author: Aditya Gudimella
Author-email: aditya.gudimella@gmail.com
Requires-Python: >=3.11,<4.0
Classifier: Programming Language :: Python :: 3
Classifier: Programming Language :: Python :: 3.11
